noop_band/__init__.py
noop_band/noop.py
noop_band-0.2.1.dist-info/LICENSE
noop_band-0.2.1.dist-info/METADATA
noop_band-0.2.1.dist-info/WHEEL
noop_band-0.2.1.dist-info/entry_points.txt
noop_band-0.2.1.dist-info/RECORD
